hydata/__init__.py
hydata/dataset.py
hydata/utils.py
hydata-0.1.1.dist-info/LICENSE.txt
hydata-0.1.1.dist-info/METADATA
hydata-0.1.1.dist-info/WHEEL
hydata-0.1.1.dist-info/RECORD
